quillmark/__init__.py
quillmark/__init__.pyi
quillmark/_quillmark.abi3.so
quillmark/py.typed
quillmark-0.32.1.dist-info/METADATA
quillmark-0.32.1.dist-info/WHEEL
quillmark-0.32.1.dist-info/RECORD
