Metadata-Version: 2.4
Name: quillmark
Version: 0.32.1
Classifier: Development Status :: 4 - Beta
Classifier: Intended Audience :: Developers
Classifier: License :: OSI Approved :: Apache Software License
Classifier: Programming Language :: Python :: 3
Classifier: Programming Language :: Python :: 3.10
Classifier: Programming Language :: Python :: 3.11
Classifier: Programming Language :: Python :: 3.12
Classifier: Programming Language :: Python :: 3.13
Classifier: Programming Language :: Rust
Classifier: Topic :: Text Processing :: Markup
Requires-Dist: pytest>=8.0 ; extra == 'dev'
Requires-Dist: maturin>=1.7,<2.0 ; extra == 'dev'
Provides-Extra: dev
Summary: Python bindings for Quillmark - template-first Markdown rendering
Keywords: markdown,pdf,typst,rendering,templates
Author: Quillmark Contributors
License: Apache-2.0
Requires-Python: >=3.10
Project-URL: Homepage, https://github.com/nibsbin/quillmark
Project-URL: Repository, https://github.com/nibsbin/quillmark
